MANIFEST.in
README.rst
setup.cfg
setup.py
jsonrequester/__init__.py
jsonrequester.egg-info/PKG-INFO
jsonrequester.egg-info/SOURCES.txt
jsonrequester.egg-info/dependency_links.txt
jsonrequester.egg-info/requires.txt
jsonrequester.egg-info/top_level.txt
tests/__init__.py
tests/unit/__init__.py
tests/unit/test_json_requestor.py