Metadata-Version: 1.0
Name: jsonrequester
Version: 0.1.4
Summary: A library for client JSON REST requests
Home-page: UNKNOWN
Author: UNKNOWN
Author-email: UNKNOWN
License: UNKNOWN
Platform: UNKNOWN
